rg22059uno/__init__.py
rg22059uno/metodoBiseccion.py
rg22059uno/metodoCramer.py
rg22059uno/metodoDescomposicionLU.py
rg22059uno/metodoGauss.py
rg22059uno/metodoGaussJordan.py
rg22059uno/metodoGaussSeidel.py
rg22059uno/metodoJacobi.py
rg22059uno-0.1.0.dist-info/licenses/LICENSE
rg22059uno-0.1.0.dist-info/METADATA
rg22059uno-0.1.0.dist-info/WHEEL
rg22059uno-0.1.0.dist-info/top_level.txt
rg22059uno-0.1.0.dist-info/RECORD
